LICENSE
MANIFEST.in
README.md
setup.cfg
setup.py
django_dropimages/__init__.py
django_dropimages/apps.py
django_dropimages/dropimagesurls.py
django_dropimages/models.py
django_dropimages/settings.py
django_dropimages/views.py
django_dropimages.egg-info/PKG-INFO
django_dropimages.egg-info/SOURCES.txt
django_dropimages.egg-info/dependency_links.txt
django_dropimages.egg-info/not-zip-safe
django_dropimages.egg-info/requires.txt
django_dropimages.egg-info/top_level.txt
django_dropimages/static/django_dropimages/css/dropzone.css
django_dropimages/static/django_dropimages/js/dropzone.js
django_dropimages/templates/django_dropimages/dropimages.html
django_dropimages/templates/django_dropimages/dropimagesjs.html
django_dropimages/templatetags/__init__.py
django_dropimages/templatetags/drop_images.py