Metadata-Version: 1.1
Name: django-dropimages
Version: 0.1.6
Summary: Uses Dropzone.js and django-braces to simplify the upload of multiple images into a collection object.
Home-page: https://github.com/sittizen/django_dropimages
Author: Simone Cittadini
Author-email: simone@sig-c.com
License: MIT
Download-URL: https://pypi.python.org/pypi/django-dropimages
Platform: UNKNOWN
Classifier: Development Status :: 2 - Pre-Alpha
Classifier: Environment :: Web Environment
Classifier: Framework :: Django
Classifier: Intended Audience :: Developers
Classifier: License :: OSI Approved :: MIT License
Classifier: Operating System :: OS Independent
Classifier: Programming Language :: Python
Classifier: Programming Language :: Python :: 2
Classifier: Programming Language :: Python :: 2.7
Classifier: Topic :: Software Development :: Libraries :: Python Modules
